pandas_market_calendars/__init__.py
pandas_market_calendars/calendar_registry.py
pandas_market_calendars/calendar_utils.py
pandas_market_calendars/class_registry.py
pandas_market_calendars/market_calendar.py
pandas_market_calendars/calendars/__init__.py
pandas_market_calendars/calendars/asx.py
pandas_market_calendars/calendars/bmf.py
pandas_market_calendars/calendars/bse.py
pandas_market_calendars/calendars/cboe.py
pandas_market_calendars/calendars/cme.py
pandas_market_calendars/calendars/cme_globex_agriculture.py
pandas_market_calendars/calendars/cme_globex_base.py
pandas_market_calendars/calendars/cme_globex_crypto.py
pandas_market_calendars/calendars/cme_globex_energy_and_metals.py
pandas_market_calendars/calendars/cme_globex_equities.py
pandas_market_calendars/calendars/cme_globex_fixed_income.py
pandas_market_calendars/calendars/cme_globex_fx.py
pandas_market_calendars/calendars/eurex.py
pandas_market_calendars/calendars/eurex_fixed_income.py
pandas_market_calendars/calendars/hkex.py
pandas_market_calendars/calendars/ice.py
pandas_market_calendars/calendars/iex.py
pandas_market_calendars/calendars/jpx.py
pandas_market_calendars/calendars/lse.py
pandas_market_calendars/calendars/mirror.py
pandas_market_calendars/calendars/nyse.py
pandas_market_calendars/calendars/ose.py
pandas_market_calendars/calendars/sifma.py
pandas_market_calendars/calendars/six.py
pandas_market_calendars/calendars/sse.py
pandas_market_calendars/calendars/tase.py
pandas_market_calendars/calendars/tsx.py
pandas_market_calendars/holidays/__init__.py
pandas_market_calendars/holidays/cme.py
pandas_market_calendars/holidays/cme_globex.py
pandas_market_calendars/holidays/cn.py
pandas_market_calendars/holidays/jp.py
pandas_market_calendars/holidays/jpx_equinox.py
pandas_market_calendars/holidays/nyse.py
pandas_market_calendars/holidays/oz.py
pandas_market_calendars/holidays/sifma.py
pandas_market_calendars/holidays/uk.py
pandas_market_calendars/holidays/us.py
pandas_market_calendars-5.2.2.dist-info/licenses/LICENSE
pandas_market_calendars-5.2.2.dist-info/licenses/NOTICE
pandas_market_calendars-5.2.2.dist-info/METADATA
pandas_market_calendars-5.2.2.dist-info/WHEEL
pandas_market_calendars-5.2.2.dist-info/top_level.txt
pandas_market_calendars-5.2.2.dist-info/RECORD
