Metadata-Version: 2.4
Name: pandas_market_calendars
Version: 5.2.2
Summary: Market and exchange trading calendars for pandas
Author-email: Ryan Sheftel <rsheftel@alumni.upenn.edu>
License: MIT
Project-URL: Homepage, https://github.com/rsheftel/pandas_market_calendars
Project-URL: Source, https://github.com/rsheftel/pandas_market_calendars
Project-URL: Documentation, https://pandas-market-calendars.readthedocs.io/en/latest/
Project-URL: Changelog, https://pandas-market-calendars.readthedocs.io/en/latest/change_log.html
Project-URL: Bug Tracker, https://github.com/rsheftel/pandas_market_calendars/issues
Keywords: trading,exchanges,markets,OTC,datetime,holiday,business days
Classifier: Development Status :: 5 - Production/Stable
Classifier: Intended Audience :: Developers
Classifier: Topic :: Software Development
Classifier: License :: OSI Approved :: MIT License
Classifier: Programming Language :: Python :: 3.8
Classifier: Programming Language :: Python :: 3.9
Classifier: Programming Language :: Python :: 3.10
Classifier: Programming Language :: Python :: 3.11
Classifier: Programming Language :: Python :: 3.12
Classifier: Programming Language :: Python :: 3.13
Classifier: Programming Language :: Python :: 3.14
Requires-Python: >=3.8
License-File: LICENSE
License-File: NOTICE
Requires-Dist: exchange-calendars>=3.3
Requires-Dist: pandas>=1.1
Provides-Extra: dev
Requires-Dist: pytest; extra == "dev"
Requires-Dist: black; extra == "dev"
Requires-Dist: pre-commit; extra == "dev"
Requires-Dist: build; extra == "dev"
Requires-Dist: twine; extra == "dev"
Dynamic: license-file
